BinGame/TicTacToe.py
BinGame/__init__.py
BinGame-0.0.1.dist-info/LICENSE
BinGame-0.0.1.dist-info/METADATA
BinGame-0.0.1.dist-info/WHEEL
BinGame-0.0.1.dist-info/top_level.txt
BinGame-0.0.1.dist-info/RECORD
